hisak/jptrans/__init__.py
hisak/jptrans/__init__.pyi
hisak/jptrans/_jptrans.cpython-311-x86_64-linux-gnu.so
hisak_jptrans-0.2.0.dist-info/METADATA
hisak_jptrans-0.2.0.dist-info/WHEEL
hisak_jptrans-0.2.0.dist-info/top_level.txt
hisak_jptrans-0.2.0.dist-info/RECORD
hisak_jptrans-0.2.0.dist-info/licenses/LICENSE
hisak_jptrans-0.2.0.dist-info/licenses/vendor/gitlab.com/HiSakDev/go-encoding/LICENSE
hisak_jptrans-0.2.0.dist-info/licenses/vendor/golang.org/x/text/LICENSE
