Metadata-Version: 2.4
Name: hisak-jptrans
Version: 0.2.0
Summary: CP932/CP51932/EUC-JP-MS japanese codecs with Go c-shared
Author-email: HiSakDev <sak.devac@gmail.com>
License-Expression: MIT AND BSD-3-Clause
Project-URL: Homepage, https://gitlab.com/HiSakDev/jptrans
Classifier: Development Status :: 4 - Beta
Classifier: Intended Audience :: Developers
Classifier: Programming Language :: Python
Classifier: Programming Language :: Python :: 3
Classifier: Programming Language :: Python :: 3 :: Only
Classifier: Programming Language :: Python :: 3.9
Classifier: Programming Language :: Python :: 3.10
Classifier: Programming Language :: Python :: 3.11
Classifier: Programming Language :: Python :: 3.12
Classifier: Programming Language :: Python :: 3.13
Requires-Python: >=3.9
License-File: LICENSE
License-File: vendor/gitlab.com/HiSakDev/go-encoding/LICENSE
License-File: vendor/golang.org/x/text/LICENSE
Dynamic: license-file
